meaning/__init__.py
meaning/meaning.py
meaning/setsql.py
meaning/version.py
meaning-0.2.3.dist-info/LICENSE
meaning-0.2.3.dist-info/METADATA
meaning-0.2.3.dist-info/WHEEL
meaning-0.2.3.dist-info/entry_points.txt
meaning-0.2.3.dist-info/top_level.txt
meaning-0.2.3.dist-info/RECORD
