Metadata-Version: 2.1
Name: meaning
Version: 0.2.3
Summary: A terminal bilingual dictionary
Home-page: https://github.com/laugh12321/meaning
Author: Laugh
Author-email: zhang26162@gmail.com
License: UNKNOWN
Platform: UNKNOWN
Requires-Dist: huepy
Requires-Dist: pangu
Requires-Dist: requests
Requires-Dist: xmltodict
Requires-Dist: sqlalchemy
Requires-Dist: terminaltables
